{"info":{"_postman_id":"248cba97-9634-4a94-ae41-ba719590090d","name":"Project Collections","schema":"https://schema.getpostman.com/json/collection/v2.1.0/collection.json","_exporter_id":"project-export"},"item":[{"name":"Demo collection azure","item":[{"name":"Login","request":{"method":"POST","header":[{"key":"sec-ch-ua-platform","value":"Windows\""},{"key":"referer","value":"https://beta8.moontechnolabs.com/tms-one/login"},{"key":"sec-ch-ua","value":"Not;A=Brand\";v=\"99\", Google Chrome\";v=\"139\", Chromium\";v=\"139\""},{"key":"sec-ch-ua-mobile","value":"?0"},{"key":"ngrok-skip-browser-warning","value":"69420"},{"key":"user-agent","value":"Mozilla/5.0 (Windows NT 10.0; Win64; x64) AppleWebKit/537.36 (KHTML, like Gecko) Chrome/139.0.0.0 Safari/537.36"},{"key":"accept","value":"application/json, text/plain, */*"},{"key":"content-type","value":"application/json"}],"url":{"raw":"https://beta8.moontechnolabs.com/tms-one-api/api/v1/auth/login","protocol":"https","host":["beta8","moontechnolabs","com"],"path":["tms-one-api","api","v1","auth","login"],"query":[]},"body":{"mode":"raw","raw":"{\"email\":\"anand@moontechnolabs.com\",\"password\":\"Test@123\"}","options":{"raw":{"language":"json"}}},"auth":{"type":"noauth"}},"response":[]},{"name":"404 status code","request":{"method":"POST","header":[{"key":"sec-ch-ua-platform","value":"Windows\""},{"key":"referer","value":"https://beta8.moontechnolabs.com/tms-one/login"},{"key":"sec-ch-ua","value":"Not;A=Brand\";v=\"99\", Google Chrome\";v=\"139\", Chromium\";v=\"139\""},{"key":"sec-ch-ua-mobile","value":"?0"},{"key":"ngrok-skip-browser-warning","value":"69420"},{"key":"user-agent","value":"Mozilla/5.0 (Windows NT 10.0; Win64; x64) AppleWebKit/537.36 (KHTML, like Gecko) Chrome/139.0.0.0 Safari/537.36"},{"key":"accept","value":"application/json, text/plain, */*"},{"key":"content-type","value":"application/json"}],"url":{"raw":"https://beta8.moontechnolabs.com/tms-one-api/api/v1/auth/loginfasdfs","protocol":"https","host":["beta8","moontechnolabs","com"],"path":["tms-one-api","api","v1","auth","loginfasdfs"],"query":[]},"body":{"mode":"raw","raw":"{\"email\":\"anand@moontechnolabs.com\",\"password\":\"Test@123\"}","options":{"raw":{"language":"json"}}},"auth":{"type":"noauth"}},"response":[]}]}]}